bincalc/__init__.py
bincalc/bincalc.py
bincalc-1.0.0.dist-info/LICENSE
bincalc-1.0.0.dist-info/METADATA
bincalc-1.0.0.dist-info/WHEEL
bincalc-1.0.0.dist-info/entry_points.txt
bincalc-1.0.0.dist-info/top_level.txt
bincalc-1.0.0.dist-info/RECORD
