Metadata-Version: 2.1
Name: bincalc
Version: 1.0.0
Summary: CLI calculator for IEEE 1541-2002 / ISO/IEC 80000-13:2008 Prefixes for Binary Multiples
Home-page: https://github.com/unixnut/bincalc
Author: Alastair Irvine
Author-email: alastair@plug.org.au
License: GNU General Public License v3
Keywords: bincalc
Platform: UNKNOWN
Classifier: Development Status :: 2 - Pre-Alpha
Classifier: Intended Audience :: Developers
Classifier: License :: OSI Approved :: GNU General Public License v3 (GPLv3)
Classifier: Natural Language :: English
Classifier: Programming Language :: Python :: 3
Classifier: Programming Language :: Python :: 3.5
Classifier: Programming Language :: Python :: 3.6
Classifier: Programming Language :: Python :: 3.7
Classifier: Programming Language :: Python :: 3.8
Requires-Python: >=3.5
Requires-Dist: binary
